Workbook

Sheet Start Here
A1: Insurance Premium Calculator
A4: Purpose | B4: Illustrative annual insurance pricing using expected claim frequency and severity.
A5: 1. Review sample history | B5: Experience contains synthetic annual data. Replace blue cells with your own data; exposure means policy-years.
A6: 2. Set assumptions | B6: Inputs controls frequency, severity, trend, expenses, and target profit. Blue cells are editable; other cells contain formulas.
A7: 3. Review the price | B7: Pricing calculates annual premium per policy and expected portfolio totals. Sensitivity compares nine frequency/severity scenarios.
A8: Units | B8: Currency is USD; frequency is claims per policy-year; severity is dollars per claim. Annual premium is dollars per policy-year.
A9: Model scope | B9: Uses a frequency × severity expected-loss model. No deductibles, limits, investment income, taxes, reinsurance, or credibility adjustments are modeled.
A10: Important | B10: Sample data and assumptions are fictional. This is a learning and planning template; it is not a rate filing or a professionally validated insurance quote.
A11: Formula updates | B11: Open in Excel or another compatible spreadsheet application to recalculate after edits. Cached initial results are included.

Sheet Experience
A1: Synthetic claims experience
A3: Year | B3: Policy-years | C3: Claim count | D3: Total claims ($) | E3: Frequency | F3: Severity ($)
A4: 2023 | B4: 900 | C4: 65 | D4: 292500 | E4: =IFERROR(C4/B4,0) -> 0.072222222 | F4: =IFERROR(D4/C4,0) -> 4500
A5: 2024 | B5: 1000 | C5: 78 | D5: 374400 | E5: =IFERROR(C5/B5,0) -> 0.078 | F5: =IFERROR(D5/C5,0) -> 4800
A6: 2025 | B6: 1100 | C6: 88 | D6: 440000 | E6: =IFERROR(C6/B6,0) -> 0.08 | F6: =IFERROR(D6/C6,0) -> 5000
A8: Total / weighted average | B8: =SUM(B4:B6) -> 3000 | C8: =SUM(C4:C6) -> 231 | D8: =SUM(D4:D6) -> 1106900 | E8: =IFERROR(C8/B8,0) -> 0.077 | F8: =IFERROR(D8/C8,0) -> 4791.7749
A10: Claims are assumed fully developed, with consistent coverage and exposure definitions. The weighted severity pools nominal historical dollars; select an appropriate base date and adjust for development or past inflation before using real data.

Sheet Inputs
A1: Pricing assumptions
A3: Assumption | B3: Value | C3: Meaning
A4: Annual claim frequency | B4: =Experience!E8 -> 0.077 | C4: Defaults to weighted historical frequency; may be overwritten.
A5: Average claim severity | B5: =Experience!F8 -> 4791.7749 | C5: Defaults to weighted historical severity; may be overwritten.
A6: Annual severity trend | B6: 0.05 | C6: Applied from the selected severity base date to the pricing period.
A7: Trend years | B7: 1 | C7: Time from selected severity base date to pricing period midpoint.
A8: Fixed expense per policy | B8: 50 | C8: Annual administration expense in dollars per policy.
A9: Variable expense ratio | B9: 0.2 | C9: Acquisition and other expenses as a fraction of premium.
A10: Target underwriting profit ratio | B10: 0.1 | C10: Expected underwriting profit divided by premium.
A11: Projected policy-years | B11: 1000 | C11: Expected annual exposure for portfolio totals.
A13: Input status | B13: =IF(AND(COUNT(B4:B11)=8,MIN(B4:B10)>=0,B11>0,SUM(B9:B10)<1),"OK","CHECK INPUTS") -> OK
A15: Zero claims produce zero historical severity; select a credible severity assumption before pricing. Validation is a convenience: pasted values can bypass it, so confirm the input status before relying on results.

Sheet Pricing
A1: Annual indicated premium
A3: Metric | B3: Value | C3: Calculation | E3: Premium component | F3: Annual dollars
A4: Trended claim severity | B4: =IF(Inputs!B13="OK",Inputs!B5*(1+Inputs!B6)^Inputs!B7,NA()) -> 5031.3636 | C4: Base severity × (1 + annual trend) ^ trend years | E4: Claims | F4: =B5 -> 387.415
A5: Expected claims cost per policy | B5: =IF(Inputs!B13="OK",Inputs!B4*B4,NA()) -> 387.415 | C5: Frequency × trended severity | E5: Fixed expense | F5: =B6 -> 50
A6: Fixed expense per policy | B6: =IF(Inputs!B13="OK",Inputs!B8,NA()) -> 50 | C6: From Inputs | E6: Variable expense | F6: =B8*Inputs!B9 -> 124.97571
A7: Available premium fraction | B7: =IF(Inputs!B13="OK",1-Inputs!B9-Inputs!B10,NA()) -> 0.7 | C7: 1 − variable expense ratio − profit ratio | E7: Profit | F7: =B8*Inputs!B10 -> 62.487857
A8: Annual premium per policy | B8: =IF(Inputs!B13="OK",(B5+B6)/B7,NA()) -> 624.87857 | C8: (Expected claims + fixed expense) / available fraction
A9: Monthly equivalent | B9: =IF(Inputs!B13="OK",B8/12,NA()) -> 52.073214 | C9: Annual premium / 12; no installment fees modeled
A10: Expected loss ratio | B10: =IF(Inputs!B13="OK",B5/B8,NA()) -> 0.61998445 | C10: Expected claims / premium
A11: Projected portfolio premium | B11: =IF(Inputs!B13="OK",B8*Inputs!B11,NA()) -> 624878.57 | C11: Annual premium × projected policy-years
A12: Projected portfolio claims | B12: =IF(Inputs!B13="OK",B5*Inputs!B11,NA()) -> 387415 | C12: Expected claims cost × projected policy-years
A13: Projected portfolio expenses | B13: =IF(Inputs!B13="OK",(B6+B8*Inputs!B9)*Inputs!B11,NA()) -> 174975.71 | C13: Fixed expenses plus variable expenses
A14: Projected underwriting profit | B14: =IF(Inputs!B13="OK",B11-B12-B13,NA()) -> 62487.857 | C14: Portfolio premium − claims − expenses

Sheet Sensitivity
A1: Annual premium sensitivity
A3: Frequency / severity | B3: 0.9 | C3: 1 | D3: 1.1
A4: 0.9 | B4: =IF(Inputs!B13="OK",(Inputs!B4*$A4*Pricing!$B$4*B$3+Inputs!B8)/(1-Inputs!B9-Inputs!B10),NA()) -> 519.72307 | C4: =IF(Inputs!B13="OK",(Inputs!B4*$A4*Pricing!$B$4*C$3+Inputs!B8)/(1-Inputs!B9-Inputs!B10),NA()) -> 569.53357 | D4: =IF(Inputs!B13="OK",(Inputs!B4*$A4*Pricing!$B$4*D$3+Inputs!B8)/(1-Inputs!B9-Inputs!B10),NA()) -> 619.34407
A5: 1 | B5: =IF(Inputs!B13="OK",(Inputs!B4*$A5*Pricing!$B$4*B$3+Inputs!B8)/(1-Inputs!B9-Inputs!B10),NA()) -> 569.53357 | C5: =IF(Inputs!B13="OK",(Inputs!B4*$A5*Pricing!$B$4*C$3+Inputs!B8)/(1-Inputs!B9-Inputs!B10),NA()) -> 624.87857 | D5: =IF(Inputs!B13="OK",(Inputs!B4*$A5*Pricing!$B$4*D$3+Inputs!B8)/(1-Inputs!B9-Inputs!B10),NA()) -> 680.22357
A6: 1.1 | B6: =IF(Inputs!B13="OK",(Inputs!B4*$A6*Pricing!$B$4*B$3+Inputs!B8)/(1-Inputs!B9-Inputs!B10),NA()) -> 619.34407 | C6: =IF(Inputs!B13="OK",(Inputs!B4*$A6*Pricing!$B$4*C$3+Inputs!B8)/(1-Inputs!B9-Inputs!B10),NA()) -> 680.22357 | D6: =IF(Inputs!B13="OK",(Inputs!B4*$A6*Pricing!$B$4*D$3+Inputs!B8)/(1-Inputs!B9-Inputs!B10),NA()) -> 741.10307
A9: Row factors multiply claim frequency; column factors multiply trended severity. Expenses and target profit remain unchanged. The center cell matches the annual premium on Pricing.
